irgateway/__init__.py
irgateway/zarinpal/__init__.py
irgateway/zarinpal/client.py
irgateway/zarinpal/enums.py
irgateway/zarinpal/errors.py
irgateway/zarinpal/types.py
irgateway-0.1.2.dist-info/licenses/LICENSE
irgateway-0.1.2.dist-info/WHEEL
irgateway-0.1.2.dist-info/METADATA
irgateway-0.1.2.dist-info/RECORD
