Metadata-Version: 2.4
Name: irgateway
Version: 0.1.2
Summary: Python SDK for Zarinpal Payment Gateway with sync and async support.
Author-email: Javad Dalirani <jdalirani82@gmail.com>
License-Expression: MIT
License-File: LICENSE
Project-URL: Homepage, https://github.com/javad2nd/irgateway
